aicapi2021_yw3760/AICAPI2021_YW3760.py
aicapi2021_yw3760/__init__.py
aicapi2021_yw3760-0.1.1.dist-info/LICENSE
aicapi2021_yw3760-0.1.1.dist-info/WHEEL
aicapi2021_yw3760-0.1.1.dist-info/METADATA
aicapi2021_yw3760-0.1.1.dist-info/RECORD
